region_cache/__init__.py
region_cache/region.py
region_cache/region_cache.py
region_cache-0.3.8.dist-info/AUTHORS.rst
region_cache-0.3.8.dist-info/LICENSE
region_cache-0.3.8.dist-info/METADATA
region_cache-0.3.8.dist-info/WHEEL
region_cache-0.3.8.dist-info/top_level.txt
region_cache-0.3.8.dist-info/RECORD
