Metadata-Version: 2.1
Name: region-cache
Version: 0.3.8
Summary: Region-based caching for Python/Flask with Redis
Home-page: https://github.com/jheard-tw/region_cache
Author: Jefferson Heard
Author-email: jheard@teamworks.com
License: MIT license
Keywords: region_cache
Platform: UNKNOWN
Classifier: Development Status :: 4 - Beta
Classifier: Intended Audience :: Developers
Classifier: License :: OSI Approved :: MIT License
Classifier: Natural Language :: English
Classifier: Programming Language :: Python :: 3
Classifier: Programming Language :: Python :: 3.9
Classifier: Programming Language :: Python :: 3.10
Requires-Dist: blinker
Requires-Dist: redis
Requires-Dist: hiredis
